{
  "lastUpdated": "2026-04-09T05:27:56.948Z",
  "latestStatement": "March 31, 2026",
  "sectors": [
    {
      "Sector": "Automobile and Auto Components",
      "15D": -14973,
      "30D": -93714,
      "90D": -104460,
      "180D": -98974,
      "360D": 19528
    },
    {
      "Sector": "Capital Goods",
      "15D": -21456,
      "30D": -51667,
      "90D": -3710,
      "180D": 21608,
      "360D": 87469
    },
    {
      "Sector": "Chemicals",
      "15D": -6589,
      "30D": -13124,
      "90D": -22833,
      "180D": -22320,
      "360D": -8382
    },
    {
      "Sector": "Construction",
      "15D": -6131,
      "30D": -34804,
      "90D": -29247,
      "180D": -17585,
      "360D": -13818
    },
    {
      "Sector": "Construction Materials",
      "15D": -1333,
      "30D": -18354,
      "90D": -16655,
      "180D": -24679,
      "360D": -15013
    },
    {
      "Sector": "Consumer Durables",
      "15D": -8348,
      "30D": -22656,
      "90D": -28120,
      "180D": -24646,
      "360D": -29412
    },
    {
      "Sector": "Consumer Services",
      "15D": -2544,
      "30D": -25504,
      "90D": -70832,
      "180D": -98833,
      "360D": -46683
    },
    {
      "Sector": "Diversified",
      "15D": -219,
      "30D": -648,
      "90D": -717,
      "180D": -949,
      "360D": -1605
    },
    {
      "Sector": "Fast Moving Consumer Goods",
      "15D": -16935,
      "30D": -42212,
      "90D": -74716,
      "180D": -90318,
      "360D": -75221
    },
    {
      "Sector": "Financial Services",
      "15D": -167095,
      "30D": -421859,
      "90D": -458613,
      "180D": -300980,
      "360D": -183680
    },
    {
      "Sector": "Forest Materials",
      "15D": -97,
      "30D": -347,
      "90D": -643,
      "180D": -751,
      "360D": -963
    },
    {
      "Sector": "Healthcare",
      "15D": -12527,
      "30D": -28000,
      "90D": -26104,
      "180D": -26678,
      "360D": -18347
    },
    {
      "Sector": "Information Technology",
      "15D": -1991,
      "30D": -25654,
      "90D": -145714,
      "180D": -97149,
      "360D": -207085
    },
    {
      "Sector": "Media, Entertainment & Publication",
      "15D": -209,
      "30D": -1134,
      "90D": -1450,
      "180D": -2884,
      "360D": -1832
    },
    {
      "Sector": "Metals & Mining",
      "15D": -6689,
      "30D": -25185,
      "90D": 10002,
      "180D": 37373,
      "360D": 57644
    },
    {
      "Sector": "Oil, Gas & Consumable Fuels",
      "15D": -20693,
      "30D": -44538,
      "90D": -77057,
      "180D": -1952,
      "360D": 24505
    },
    {
      "Sector": "Power",
      "15D": -7855,
      "30D": -7841,
      "90D": 9276,
      "180D": -1779,
      "360D": -10314
    },
    {
      "Sector": "Realty",
      "15D": -11944,
      "30D": -24263,
      "90D": -39527,
      "180D": -40363,
      "360D": -48964
    },
    {
      "Sector": "Services",
      "15D": -6746,
      "30D": -24984,
      "90D": -28996,
      "180D": -35558,
      "360D": -3913
    },
    {
      "Sector": "Telecommunication",
      "15D": 897,
      "30D": -19503,
      "90D": -63208,
      "180D": -1664,
      "360D": 42150
    },
    {
      "Sector": "Textiles",
      "15D": -29,
      "30D": -1331,
      "90D": -2827,
      "180D": -5336,
      "360D": -6233
    },
    {
      "Sector": "Utilities",
      "15D": -120,
      "30D": -207,
      "90D": -391,
      "180D": -579,
      "360D": -711
    },
    {
      "Sector": "Sovereign",
      "15D": 0,
      "30D": 0,
      "90D": 0,
      "180D": 0,
      "360D": 0
    },
    {
      "Sector": "Others",
      "15D": -2238,
      "30D": -3746,
      "90D": -3359,
      "180D": 5454,
      "360D": 6942
    },
    {
      "Sector": "Grand Total",
      "15D": -315864,
      "30D": -931274,
      "90D": -1179900,
      "180D": -829542,
      "360D": -433936
    }
  ]
}